wield/collection/__init__.py
wield/collection/_version.py
wield-0.5.0.dist-info/Apache-2.0.txt
wield-0.5.0.dist-info/CC0-1.0.txt
wield-0.5.0.dist-info/METADATA
wield-0.5.0.dist-info/NOTICE
wield-0.5.0.dist-info/WHEEL
wield-0.5.0.dist-info/top_level.txt
wield-0.5.0.dist-info/RECORD
