Metadata-Version: 2.1
Name: wield
Version: 0.5.0
Summary: Toolkit for modeling interferometers, circuits, signals, and control systems
Home-page: https://github.com/wieldphysics/wield-collection
Author: Lee McCuller
Author-email: mcculler@caltech.edu
License: Apache-2.0
Project-URL: Bug Tracker, https://github.com/wieldphysics/wield-namespace/issues
Project-URL: Source Code, https://github.com/wieldphysics/wield-namespace
Classifier: Intended Audience :: Science/Research
Classifier: License :: OSI Approved :: Apache Software License
Classifier: Operating System :: OS Independent
Classifier: Programming Language :: Python
Classifier: Programming Language :: Python :: 3
Classifier: Topic :: Scientific/Engineering :: Physics
License-File: LICENSES/Apache-2.0.txt
License-File: LICENSES/CC0-1.0.txt
License-File: NOTICE
